my_sort/__init__.py
my_sort/main.py
my_sort_yura_maksym-0.1.2.dist-info/licenses/LICENSE
my_sort_yura_maksym-0.1.2.dist-info/METADATA
my_sort_yura_maksym-0.1.2.dist-info/WHEEL
my_sort_yura_maksym-0.1.2.dist-info/entry_points.txt
my_sort_yura_maksym-0.1.2.dist-info/top_level.txt
my_sort_yura_maksym-0.1.2.dist-info/RECORD
