Metadata-Version: 2.4
Name: my-sort-Yura-Maksym
Version: 0.1.2
Summary: Кастомна реалізація утиліти sort на Python.
Home-page: https://github.com/Ваш_Акаунт/my-sort
Author: Yura-Maksym
Author-email: your_email@example.com
Classifier: Programming Language :: Python :: 3
Classifier: License :: OSI Approved :: MIT License
Classifier: Operating System :: OS Independent
Requires-Python: >=3.7
License-File: LICENSE
Requires-Dist: click
Dynamic: author
Dynamic: author-email
Dynamic: classifier
Dynamic: description
Dynamic: description-content-type
Dynamic: home-page
Dynamic: license-file
Dynamic: requires-dist
Dynamic: requires-python
Dynamic: summary
